{
  "db_name": "SQLite",
  "query": "\n            SELECT user.id, username, email\n            FROM user\n            JOIN session ON user.id = session.user_id\n            WHERE session.id = ?\n            AND last_used_at + idle_duration > CURRENT_TIMESTAMP\n            ",
  "describe": {
    "columns": [
      {
        "name": "id",
        "ordinal": 0,
        "type_info": "Blob"
      },
      {
        "name": "username",
        "ordinal": 1,
        "type_info": "Text"
      },
      {
        "name": "email",
        "ordinal": 2,
        "type_info": "Text"
      }
    ],
    "parameters": {
      "Right": 1
    },
    "nullable": [
      false,
      false,
      true
    ]
  },
  "hash": "b9d605d41c88971eb327c665763e96946bc4ccc853bc15779f806bca6c17c60e"
}
